ytools/VERSION
ytools/__init__.py
ytools/error.py
ytools/log.py
ytools/version.py
ytools/alert/__init__.py
ytools/alert/wechat.py
ytools/arq/__init__.py
ytools/arq/setting.py
ytools/arq/client/__init__.py
ytools/arq/client/agent.py
ytools/arq/client/base.py
ytools/arq/client/client.py
ytools/arq/task/__init__.py
ytools/arq/task/task.py
ytools/auto_driver/__init__.py
ytools/auto_driver/rpa_base.py
ytools/auto_driver/track.py
ytools/auto_driver/dp/__init__.py
ytools/auto_driver/dp/route.py
ytools/auto_driver/dp/route_by_fetch.py
ytools/auto_driver/dp/rpa.py
ytools/network/__init__.py
ytools/network/header.py
ytools/network/request.py
ytools/network/response.py
ytools/utils/__init__.py
ytools/utils/cache.py
ytools/utils/cache_utils.py
ytools/utils/counter.py
ytools/utils/date.py
ytools/utils/encrypt.py
ytools/utils/extractors.py
ytools/utils/file.py
ytools/utils/host_ip.py
ytools/utils/magic.py
ytools/utils/magic_for_class.py
ytools/utils/nodes.py
ytools/utils/package.py
ytools/utils/quiter.py
ytools/utils/sign.py
ytools/utils/track.py
ytools/utils/variable.py
why_tools-0.2.17.dist-info/METADATA
why_tools-0.2.17.dist-info/WHEEL
why_tools-0.2.17.dist-info/top_level.txt
why_tools-0.2.17.dist-info/RECORD
