Metadata-Version: 2.4
Name: why-tools
Version: 0.2.17
Summary: 为什么还要使用别的工具呢？
Home-page: https://github.com/yintian710/whytools
Author: yintian
Author-email: yintian710@gmail.com
License: MIT
Keywords: ytools
Classifier: Programming Language :: Python
Classifier: Programming Language :: Python :: 3.8
Classifier: Programming Language :: Python :: Implementation :: CPython
Classifier: Programming Language :: Python :: Implementation :: PyPy
Requires-Python: >=3.8.0
Requires-Dist: loguru==0.7.3
Requires-Dist: importlib-metadata==7.1.0
Requires-Dist: better_exceptions==0.3.3
Dynamic: author
Dynamic: author-email
Dynamic: classifier
Dynamic: description
Dynamic: description-content-type
Dynamic: home-page
Dynamic: keywords
Dynamic: license
Dynamic: requires-dist
Dynamic: requires-python
Dynamic: summary
